README.rst
setup.py
dnstk/__init__.py
dnstk/client.py
dnstk/file.py
dnstk/packet.py
dnstk/resources.py
dnstk/server.py
dnstk/utils.py
dnstk.egg-info/PKG-INFO
dnstk.egg-info/SOURCES.txt
dnstk.egg-info/dependency_links.txt
dnstk.egg-info/entry_points.txt
dnstk.egg-info/requires.txt
dnstk.egg-info/top_level.txt