Metadata-Version: 1.1
Name: dnstk
Version: 0.1.1
Summary: Python DNS toolkit
Home-page: https://github.com/kylef/dnstk/
Author: Kyle Fuller
Author-email: inbox@kylefuller.co.uk
License: BSD
Platform: UNKNOWN
Classifier: Development Status :: 4 - Beta
Classifier: Intended Audience :: Developers
Classifier: License :: OSI Approved :: BSD License
Classifier: Operating System :: OS Independent
Classifier: Programming Language :: Python :: 3.2
Classifier: Programming Language :: Python :: 3.3
Classifier: Topic :: Internet :: Name Service (DNS)
Classifier: Topic :: Software Development :: Libraries
